zipstream/__init__.py
zipstream/ng.py
zipstream/server.py
zipstream_ng-1.8.0.dist-info/LICENSE
zipstream_ng-1.8.0.dist-info/METADATA
zipstream_ng-1.8.0.dist-info/WHEEL
zipstream_ng-1.8.0.dist-info/entry_points.txt
zipstream_ng-1.8.0.dist-info/top_level.txt
zipstream_ng-1.8.0.dist-info/RECORD
