Metadata-Version: 2.1
Name: zipstream-ng
Version: 1.8.0
Summary: A modern and easy to use streamable zip file generator
Home-page: https://github.com/pR0Ps/zipstream-ng
License: LGPLv3
Project-URL: Source, https://github.com/pR0Ps/zipstream-ng
Project-URL: Changelog, https://github.com/pR0Ps/zipstream-ng/blob/master/CHANGELOG.md
Classifier: Programming Language :: Python :: 3
Classifier: Programming Language :: Python :: 3.5
Classifier: Programming Language :: Python :: 3.6
Classifier: Programming Language :: Python :: 3.7
Classifier: Programming Language :: Python :: 3.8
Classifier: Programming Language :: Python :: 3.9
Classifier: Programming Language :: Python :: 3.10
Classifier: Programming Language :: Python :: 3.11
Classifier: Programming Language :: Python :: 3.12
Classifier: Operating System :: OS Independent
Classifier: Topic :: System :: Archiving :: Compression
Classifier: License :: OSI Approved :: GNU Lesser General Public License v3 (LGPLv3)
Requires-Python: >=3.5.0
License-File: LICENSE
Provides-Extra: tests
Requires-Dist: pytest; extra == "tests"
Requires-Dist: pytest-cov; extra == "tests"
